<Properties StartupConfiguration="{DC91D114-5CEF-4199-8888-390EAEC9BB0E}|Default">
  <MonoDevelop.Ide.Workbench ActiveDocument="WebApplication2/Views/Registroes/Create.cshtml">
    <Files>
      <File FileName="WebApplication2/Views/Shared/_Layout.cshtml" Line="17" Column="1" />
      <File FileName="WebApplication2/Views/Registroes/Create.cshtml" Line="158" Column="55" />
    </Files>
    <Pads>
      <Pad Id="ProjectPad">
        <State name="__root__">
          <Node name="WebApplication2" expanded="True">
            <Node name="WebApplication2" expanded="True">
              <Node name="Views" expanded="True">
                <Node name="Registroes" expanded="True">
                  <Node name="Create.cshtml" selected="True" />
                </Node>
              </Node>
            </Node>
            <Node name="WebApplication3" expanded="True">
              <Node name="Dependencies" expanded="True">
                <Node name="FrameworkReferences" expanded="True" />
              </Node>
              <Node name="Controllers" expanded="True" />
            </Node>
          </Node>
        </State>
      </Pad>
    </Pads>
  </MonoDevelop.Ide.Workbench>
  <MonoDevelop.Ide.ItemProperties.WebApplication2 PreferredExecutionTarget="/Applications/Google Chrome.app" />
  <MonoDevelop.Ide.DebuggingService.PinnedWatches />
  <MonoDevelop.Ide.Workspace ActiveConfiguration="Debug" />
  <MonoDevelop.Ide.DebuggingService.Breakpoints>
    <BreakpointStore />
  </MonoDevelop.Ide.DebuggingService.Breakpoints>
  <MultiItemStartupConfigurations />
</Properties>